{
  "date": "2026-03-02",
  "highlights": {
    "bullets": [
      "핵심: 이 대통령이 다주택자에게 5월 9일까지 집을 팔 것을 촉구했다.",
      "핵심: 이재명 대통령은 강요 대신 세금·금융 등 제도 설계로 유인구조를 바꾸겠다고 말했다.",
      "트렌드: 부동산 정책 변화와 지역별 공급 변동이 시장 유인과 수급에 영향을 미치고 있다."
    ],
    "topTopics": [
      "Market",
      "Supply",
      "Policy",
      "Rental"
    ],
    "stats": {
      "collected": 11,
      "deduped": 11
    }
  },
  "cards": [
    {
      "id": "realestate_0001",
      "tab": "realestate",
      "publishedAt": "2026-03-01T21:00:03+09:00",
      "source": "매일경제(부동산)",
      "title": "李대통령 “다주택자가 집 안팔고 버티면 손실되게 할 것”",
      "summary": [
        "이 대통령이 다주택자에게 5월 9일까지 집을 팔 것을 촉구했다.",
        "정부는 다주택 보유자가 팔지 않고 버티면 세제와 정책으로 손실을 입히겠다고 밝혔다.",
        "발언은 다주택 규제 강화와 주택시장 안정화 의지를 분명히 보여준다."
      ],
      "whyItMatters": "부동산 투기 억제와 주거시장 안정화를 위해 보유세·과세·규제 강화 가능성을 예고해 시장과 투자자 행동에 즉각적 영향을 미치기 때문이다.",
      "topics": [
        "Policy",
        "Tax",
        "Market",
        "Supply"
      ],
      "status": "SHIFTING",
      "hash": "5df44b97e238652cbc451055a45c3f48d1418423a45a7bda3a91a3ce23ec5559",
      "url": "https://www.mk.co.kr/news/realestate/11975873"
    },
    {
      "id": "realestate_0002",
      "tab": "realestate",
      "publishedAt": "2026-03-01T20:43:37+09:00",
      "source": "매일경제(부동산)",
      "title": "이재명 “다주택 ‘팔아라’ ‘사지마라’ 강요할 필요없어…세금 금융 등 철저히 설계”",
      "summary": [
        "이재명 대통령은 다주택자에게 팔거나 사지 말라고 강요할 필요가 없다고 밝혔다.",
        "투기는 투기가 가능하게 만든 정치·정부 책임이라며 세금·금융 등 제도 설계로 과거 선택이 손실이 되게 하겠다고 말했다.",
        "강제적 처분 대신 세제·금융정책으로 시장 행태를 유도하는 정책 방향을 제시했다."
      ],
      "whyItMatters": "대통령의 발언은 부동산 세제·금융정책을 통해 시장 유인구조를 변경하겠다는 방향 전환을 시사하기 때문이다.",
      "topics": [
        "Policy",
        "Tax",
        "Market",
        "Mortgage"
      ],
      "status": "SHIFTING",
      "hash": "ca8c6025d24b0899bab5ae352a966094b9e437aead91a65074becdc9daa1c2b0",
      "url": "https://www.mk.co.kr/news/economy/11975867"
    },
    {
      "id": "realestate_0003",
      "tab": "realestate",
      "publishedAt": "2026-03-01T14:00:00+09:00",
      "source": "헤럴드경제(부동산)",
      "title": "지방 분양 단지 공급 감소 속 들어서는 두산건설, ‘두산위브더제니스 센트럴 천안’",
      "summary": [
        "2026년 지방 아파트 분양 물량이 145개 단지·9만1,571가구로 집계돼 2012년 이후 최저치를 기록했다.",
        "전년 대비 공급이 약 26% 감소하며 신축 아파트의 희소성이 커지고 있다.",
        "공급 축소 국면에서 두산건설이 ‘두산위브더제니스 센트럴 천안’을 분양하며 지방 시장에 재진입했다."
      ],
      "whyItMatters": "경기 침체와 분양 위축으로 공급이 급감하면서 신축의 희소성으로 인한 가격·수요 반등 가능성이 부각되고 있기 때문입니다.",
      "topics": [
        "Supply",
        "Market",
        "Construction"
      ],
      "status": "SHIFTING",
      "hash": "6bc21f6fdf52a6190147baaf29118bb38fecbd9ae418e301018d75935e083841",
      "url": "https://biz.heraldcorp.com/article/10684079"
    },
    {
      "id": "realestate_0004",
      "tab": "realestate",
      "publishedAt": "2026-03-01T16:52:30+09:00",
      "source": "한국경제(부동산)",
      "title": "천안 '업성 푸르지오' 1460가구 공급",
      "summary": [
        "천안에 '업성 푸르지오' 아파트 1460가구가 공급된다.",
        "대단지는 지역 주택 공급을 대폭 늘려 시장에 영향을 줄 것으로 보인다.",
        "분양 시기와 가격에 따라 청약 경쟁과 주변 시세 변동이 예상된다."
      ],
      "whyItMatters": "대규모 공급은 지역 주택 수급과 시세에 직접적인 영향을 미치기 때문이다.",
      "topics": [
        "Supply",
        "Market",
        "Construction"
      ],
      "status": "NEW",
      "hash": "84d21b6dae854d216be7bff0a5d1d67f1afd863e35f06ade374036e454fb2d20",
      "url": "https://www.hankyung.com/article/2026030125161"
    }
  ]
}