{
  "date": "2026-05-13",
  "highlights": {
    "bullets": [
      "핵심: TAIYO YUDEN의 다층 전력 인덕터와 MLCC로 차세대 집적 전압 레귤레이터가 소개되었다.",
      "핵심: 애플과 인텔의 파운드리 협력 보도가 나왔다.",
      "트렌드: 제조 역량과 제품 경쟁력 강화를 위한 기술 개발과 협력이 공통으로 부각되었다."
    ],
    "topTopics": [
      "Competition",
      "Manufacturing",
      "Roadmap",
      "Demand"
    ],
    "stats": {
      "collected": 5,
      "deduped": 5
    }
  },
  "cards": [
    {
      "id": "semiconductor_0001",
      "tab": "semiconductor",
      "publishedAt": "2026-05-13T02:00:00+09:00",
      "source": "EE Times",
      "title": "Next-Gen Integrated Voltage Regulators with Multilayer Power Inductors and Ceramic Capacitors",
      "summary": [
        "TAIYO YUDEN의 다층 전력 인덕터와 MLCC를 활용한 차세대 집적 전압 레귤레이터가 소개되었습니다.",
        "이 기술은 AI 및 GPU 애플리케이션에서 전력 효율과 소형화, 고주파 응답 성능을 개선하는 것을 목표로 합니다.",
        "서버·고성능 컴퓨팅 수요 증가로 관련 전력 부품 수요와 경쟁이 더욱 심화될 전망입니다."
      ],
      "whyItMatters": "AI·GPU의 전력 요구가 늘면서 전력부품의 효율 개선이 시스템 성능과 에너지 소비에 직접적 영향을 미치기 때문입니다.",
      "topics": [
        "Manufacturing",
        "Demand",
        "Competition",
        "Roadmap"
      ],
      "status": "ONGOING",
      "hash": "d3336fd0d2816a49af50a9e884d4f3d43bf54a5ed94da72a73db681ac9739f8e",
      "url": "https://www.eetimes.com/next-gen-integrated-voltage-regulators-with-multilayer-power-inductors-and-ceramic-capacitors/"
    },
    {
      "id": "semiconductor_0002",
      "tab": "semiconductor",
      "publishedAt": "2026-05-12T22:09:09+09:00",
      "source": "EE Times",
      "title": "Apple-Intel Foundry Deal Could Reshape U.S. Chip Manufacturing",
      "summary": [
        "애플과 인텔의 파운드리 협력 보도가 나왔다.",
        "이 협력은 미국 반도체 제조 역량과 공급망 구조를 바꿀 잠재력이 있다.",
        "다만 보도는 TSMC 집중에 대한 상징적 헤지일 가능성도 제기한다."
      ],
      "whyItMatters": "미국 내 파운드리 다변화가 산업 경쟁력과 정책 우선순위에 직접적인 영향을 줄 수 있기 때문이다.",
      "topics": [
        "Manufacturing",
        "Competition",
        "Policy"
      ],
      "status": "SHIFTING",
      "hash": "e60248822f76005d22a2da674089ee5af9e93ddc912ffc890ec8c73afa215af8",
      "url": "https://www.eetimes.com/apple-intel-foundry-deal-could-reshape-u-s-chip-manufacturing/"
    },
    {
      "id": "semiconductor_0003",
      "tab": "semiconductor",
      "publishedAt": "2026-05-13T06:20:00+09:00",
      "source": "Samsung Newsroom",
      "title": "Samsung Launches One UI 9 Beta for Galaxy S26 Series Users",
      "summary": [
        "삼성이 Galaxy S26 시리즈를 대상으로 One UI 9 베타 프로그램을 시작했다.",
        "One UI 9는 Android 17 기반으로 창작 도구 확장, 맞춤화 옵션 강화, 접근성 향상 및 보안 강화 기능을 제공한다.",
        "베타는 이번 주부터 진행되며 정식 버전은 이후 공개될 예정이다."
      ],
      "whyItMatters": "플랫폼 업데이트는 사용자 경험과 보안 개선을 통해 제품 경쟁력 및 시장 포지셔닝에 직접적인 영향을 주기 때문이다.",
      "topics": [
        "Roadmap",
        "Competition"
      ],
      "status": "ONGOING",
      "hash": "7f97e13177e6caeaa790627468e62ccade3550d833c936997f694bfc78f194c2",
      "url": "https://news.samsung.com/global/samsung-launches-one-ui-9-beta-for-galaxy-s26-series-users"
    }
  ]
}