{
  "range": {
    "from": "2026-01-11",
    "to": "2026-02-09"
  },
  "kpis": {
    "collected": 27,
    "deduped": 27,
    "uniqueTopics": 7,
    "marketShare": {
      "Roadmap": 28,
      "Investment": 25,
      "Competition": 20,
      "Demand": 15,
      "Policy": 13,
      "Other": 0
    }
  },
  "weeklyData": [
    {
      "week": "Week 1 (01/11-01/17)",
      "topicCounts": {
        "Roadmap": 0,
        "Investment": 0,
        "Competition": 0,
        "Demand": 0,
        "Policy": 0
      }
    },
    {
      "week": "Week 2 (01/18-01/24)",
      "topicCounts": {
        "Roadmap": 0,
        "Investment": 0,
        "Competition": 0,
        "Demand": 0,
        "Policy": 0
      }
    },
    {
      "week": "Week 3 (01/25-01/31)",
      "topicCounts": {
        "Roadmap": 11,
        "Investment": 10,
        "Competition": 8,
        "Demand": 7,
        "Policy": 5
      }
    },
    {
      "week": "Week 4 (02/01-02/07)",
      "topicCounts": {
        "Roadmap": 9,
        "Investment": 9,
        "Competition": 8,
        "Demand": 3,
        "Policy": 6
      }
    },
    {
      "week": "Week 5 (02/08-02/09)",
      "topicCounts": {
        "Roadmap": 0,
        "Investment": 0,
        "Competition": 0,
        "Demand": 0,
        "Policy": 0
      }
    }
  ],
  "topIssues": [
    {
      "id": "ev-1",
      "status": "NEW",
      "title": "BYD 투자로 급부상한 자율주행 배터리 교환식 전기 광산 트럭",
      "summary": "중국 Boonray가 자율주행·배터리 교환식 전기 광산 트럭을 개발했고, BYD가 수백만 달러를 투자하며 상용화와 대규모 생산의 전환점이 되고 있다. 이는 대형 상용EV 및 특수 산업용 전동화 시장 확대의 신호탄으로, 배터리 스왑 모델의 사업성 검증에도 의미가 크다.",
      "articleCount": 1,
      "relatedArticles": [
        {
          "source": "Electrek",
          "title": "Autonomous, battery-swap mining truck gets big-buck boost from BYD [video]",
          "url": "https://electrek.co/2026/02/07/autonomous-battery-swap-mining-truck-gets-big-buck-boost-from-byd/"
        }
      ]
    },
    {
      "id": "ev-2",
      "status": "NEW",
      "title": "세계 최초 소듐-이온 배터리 EV 등장, 원가·리스크 구조 재편 가능성",
      "summary": "CATL과 장안자동차가 세계 최초 소듐-이온 배터리 탑재 승용 EV를 공개했다. 리튬 대비 저렴하고 공급 리스크가 적은 나트륨 기반으로, 원재료 비용과 안전성 측면에서 강점을 보여 대중형 EV의 가격 경쟁력과 공급망 다변화에 중장기적으로 큰 변수가 될 수 있다.",
      "articleCount": 1,
      "relatedArticles": [
        {
          "source": "Electrek",
          "title": "The world’s first sodium-ion battery EV is here and it could be a game changer",
          "url": "https://electrek.co/2026/02/05/first-sodium-ion-battery-ev-debuts-game-changer/"
        }
      ]
    },
    {
      "id": "ev-3",
      "status": "ONGOING",
      "title": "글로벌 전력 수요 급증과 EV 확산이 직면한 전력망 병목 리스크",
      "summary": "IEA는 전력 수요가 빠르게 늘고 있지만 전력망 투자가 이를 따라가지 못해 공급 제약과 안정성 리스크가 커지고 있다고 경고한다. EV·재생에너지 확대와 맞물려 충전 인프라, 분산자원 연계, 그리드 현대화 정책·투자가 동시다발적으로 요구되는 상황이다.",
      "articleCount": 1,
      "relatedArticles": [
        {
          "source": "Electrek",
          "title": "IEA: Electricity demand is rising fast, and grids can’t keep up",
          "url": "https://electrek.co/2026/02/05/iea-electricity-demand-is-rising-fast-and-grids-cant-keep-up/"
        }
      ]
    },
    {
      "id": "ev-4",
      "status": "SHIFTING",
      "title": "테슬라의 고급 세단 단종과 ‘서비스로서의 운송’ 전환",
      "summary": "테슬라는 모델 S·X 단종과 함께 새로운 대중형 승용 EV 계획이 없다고 밝히고, 제조 중심에서 모빌리티 서비스 중심으로 전략 축을 옮기고 있다. 이는 기존 완성차 경쟁 구조에서 한발 비켜나면서도 브랜드·수익성·자율주행 기술 상용화 방식에 중대한 변화를 예고한다.",
      "articleCount": 1,
      "relatedArticles": [
        {
          "source": "Electrek",
          "title": "Tesla is committing automotive suicide",
          "url": "https://electrek.co/2026/01/29/tesla-committing-automotive-suicide/"
        }
      ]
    },
    {
      "id": "ev-5",
      "status": "NEW",
      "title": "테슬라 중국 AI 트레이닝 센터로 가속되는 FSD 현지 개발",
      "summary": "테슬라가 중국 내 AI 학습 센터를 구축하며 현지 데이터 기반 FSD 개발에 속도를 내고 있다. 중국 규제 환경과 데이터 보안 이슈를 고려한 로컬 인프라 확보로, 자율주행 기능의 성능 향상과 중국 시장 맞춤형 서비스 출시가 한층 빨라질 수 있다.",
      "articleCount": 1,
      "relatedArticles": [
        {
          "source": "Electrek",
          "title": "Tesla now has AI training capability in China, a critical step for Full Self-Driving",
          "url": "https://electrek.co/2026/02/06/tesla-ai-training-capability-china-critical-step-full-self-driving/"
        }
      ]
    }
  ]
}