{
  "range": {
    "from": "2026-06-11",
    "to": "2026-06-17"
  },
  "kpis": {
    "collected": 13,
    "deduped": 13,
    "uniqueTopics": 6
  },
  "topTopics": [
    {
      "name": "Roadmap",
      "count": 11
    },
    {
      "name": "Competition",
      "count": 10
    },
    {
      "name": "Investment",
      "count": 6
    },
    {
      "name": "Manufacturing",
      "count": 6
    }
  ],
  "topicTrend": [
    {
      "date": "2026-06-11",
      "dayOfWeek": "Thu",
      "topic": "Roadmap",
      "count": 2
    },
    {
      "date": "2026-06-11",
      "dayOfWeek": "Thu",
      "topic": "Competition",
      "count": 1
    },
    {
      "date": "2026-06-11",
      "dayOfWeek": "Thu",
      "topic": "Investment",
      "count": 1
    },
    {
      "date": "2026-06-11",
      "dayOfWeek": "Thu",
      "topic": "Manufacturing",
      "count": 0
    },
    {
      "date": "2026-06-12",
      "dayOfWeek": "Fri",
      "topic": "Roadmap",
      "count": 2
    },
    {
      "date": "2026-06-12",
      "dayOfWeek": "Fri",
      "topic": "Competition",
      "count": 2
    },
    {
      "date": "2026-06-12",
      "dayOfWeek": "Fri",
      "topic": "Investment",
      "count": 2
    },
    {
      "date": "2026-06-12",
      "dayOfWeek": "Fri",
      "topic": "Manufacturing",
      "count": 3
    },
    {
      "date": "2026-06-13",
      "dayOfWeek": "Sat",
      "topic": "Roadmap",
      "count": 1
    },
    {
      "date": "2026-06-13",
      "dayOfWeek": "Sat",
      "topic": "Competition",
      "count": 0
    },
    {
      "date": "2026-06-13",
      "dayOfWeek": "Sat",
      "topic": "Investment",
      "count": 1
    },
    {
      "date": "2026-06-13",
      "dayOfWeek": "Sat",
      "topic": "Manufacturing",
      "count": 1
    },
    {
      "date": "2026-06-14",
      "dayOfWeek": "Sun",
      "topic": "Roadmap",
      "count": 0
    },
    {
      "date": "2026-06-14",
      "dayOfWeek": "Sun",
      "topic": "Competition",
      "count": 1
    },
    {
      "date": "2026-06-14",
      "dayOfWeek": "Sun",
      "topic": "Investment",
      "count": 0
    },
    {
      "date": "2026-06-14",
      "dayOfWeek": "Sun",
      "topic": "Manufacturing",
      "count": 0
    },
    {
      "date": "2026-06-15",
      "dayOfWeek": "Mon",
      "topic": "Roadmap",
      "count": 1
    },
    {
      "date": "2026-06-15",
      "dayOfWeek": "Mon",
      "topic": "Competition",
      "count": 1
    },
    {
      "date": "2026-06-15",
      "dayOfWeek": "Mon",
      "topic": "Investment",
      "count": 0
    },
    {
      "date": "2026-06-15",
      "dayOfWeek": "Mon",
      "topic": "Manufacturing",
      "count": 0
    },
    {
      "date": "2026-06-16",
      "dayOfWeek": "Tue",
      "topic": "Roadmap",
      "count": 4
    },
    {
      "date": "2026-06-16",
      "dayOfWeek": "Tue",
      "topic": "Competition",
      "count": 4
    },
    {
      "date": "2026-06-16",
      "dayOfWeek": "Tue",
      "topic": "Investment",
      "count": 1
    },
    {
      "date": "2026-06-16",
      "dayOfWeek": "Tue",
      "topic": "Manufacturing",
      "count": 2
    },
    {
      "date": "2026-06-17",
      "dayOfWeek": "Wed",
      "topic": "Roadmap",
      "count": 1
    },
    {
      "date": "2026-06-17",
      "dayOfWeek": "Wed",
      "topic": "Competition",
      "count": 1
    },
    {
      "date": "2026-06-17",
      "dayOfWeek": "Wed",
      "topic": "Investment",
      "count": 1
    },
    {
      "date": "2026-06-17",
      "dayOfWeek": "Wed",
      "topic": "Manufacturing",
      "count": 0
    }
  ],
  "topIssues": [
    {
      "id": 1,
      "status": "NEW",
      "title": "AMD의 MEXT 인수로 AI ‘메모리 월’ 돌파 시도",
      "summary": "AMD가 메모리 전문 기업 MEXT를 인수하며 AI 워크로드에서 병목으로 지적돼 온 ‘메모리 월’ 문제를 정면 돌파하려 하고 있습니다. 이는 대규모 AI 모델 실행 시 메모리 대역폭·지연을 줄여 비용을 낮추고 성능을 끌어올리려는 전략적 투자로, GPU·AI 가속기 경쟁 구도를 흔들 수 있는 중장기 기술 전환 이슈입니다.",
      "articleCount": 1,
      "relatedArticles": [
        {
          "source": "EE Times",
          "title": "AMD Snaps MEXT to Break the Memory Wall",
          "url": "https://www.eetimes.com/amd-snaps-mext-to-break-the-memory-wall/"
        }
      ]
    },
    {
      "id": 2,
      "status": "SHIFTING",
      "title": "GlobalFoundries, AI 스케일업용 개방형 표준 실리콘 첫 지원",
      "summary": "GlobalFoundries가 AI 데이터센터 확장을 위한 개방형 인터커넥트 표준(OCI MSA)을 지원하는 최초의 상용 실리콘을 발표했습니다. 이로써 AI 가속기·메모리·네트워크 간 상호운용성과 모듈형 확장이 쉬워져, 특정 벤더 종속에서 벗어나려는 클라우드·데이터센터 고객의 선택지가 넓어지고 파운드리 경쟁 구도에도 변화를 줄 수 있는 이슈입니다.",
      "articleCount": 1,
      "relatedArticles": [
        {
          "source": "EE Times",
          "title": "GlobalFoundries: First Chipmaker to Support Open Standard for AI Scale Up",
          "url": "https://www.eetimes.com/globalfoundries-first-chipmaker-to-support-open-standard-for-ai-scale-up/"
        }
      ]
    },
    {
      "id": 3,
      "status": "ONGOING",
      "title": "LNS 기반 초저전력 AI 칩 테이프아웃, GPU 대체지 후보 부상",
      "summary": "Tensordyne이 로그 수 체계(LNS)를 활용한 AI 전용 칩의 테이프아웃을 완료하며, 기존 GPU 대비 토큰당 전력 소모를 약 10배 줄였다고 주장하고 있습니다. 소비 전력·발열·TCO를 중시하는 엣지·데이터센터 AI 모두에 새로운 아키텍처 옵션이 부상한 것으로, 향후 검증 결과에 따라 차세대 전력 효율형 AI 반도체 시장 판도를 바꿀 가능성이 있습니다.",
      "articleCount": 1,
      "relatedArticles": [
        {
          "source": "EE Times",
          "title": "Tensordyne Tapes Out LNS-Based AI Chip, Claims Huge Power Advantages",
          "url": "https://www.eetimes.com/tensordyne-tapes-out-lns-based-ai-chip-claims-huge-power-advantages/"
        }
      ]
    },
    {
      "id": 4,
      "status": "NEW",
      "title": "UCLA 1억2500만달러 반도체 허브, 고영향 AI·공정 연구 가속",
      "summary": "UCLA가 1억2500만 달러 규모의 반도체 허브를 설립하며 ‘점진적’ 개선이 아닌 고영향 혁신을 목표로 AI 중심 반도체 연구를 추진합니다. 소재·공정·아키텍처 전반에서 병목을 해소해 차세대 칩 설계·제조 역량을 확보하려는 시도로, 미국 내 공급망 강화와 인력 양성, 대학-산업계 협력 확대의 거점 역할이 예상됩니다.",
      "articleCount": 1,
      "relatedArticles": [
        {
          "source": "EE Times",
          "title": "UCLA’s $125M Semiconductor Hub: “We Want High Impact, Not Incremental Research”",
          "url": "https://www.eetimes.com/uclas-125m-semiconductor-hub-we-want-high-impact-not-incremental-research/"
        }
      ]
    },
    {
      "id": 5,
      "status": "ONGOING",
      "title": "자율 항공우주·방위 시스템에서의 반도체 수요 확대",
      "summary": "EE Times 6월호는 자율 항공우주 및 방위 시스템에 초점을 맞추며, 궤도 데이터센터부터 AI 기반 드론까지 고신뢰·고성능 반도체의 역할을 다루고 있습니다. 군수·우주 영역에서의 고내구성 칩, 센서, 통신·연산 SoC 수요가 늘고 있어, 전통적인 모바일·PC·서버 외에 국방·우주가 반도체 성장 축으로 부상하는 흐름을 보여줍니다.",
      "articleCount": 1,
      "relatedArticles": [
        {
          "source": "EE Times",
          "title": "EE Times Magazine – June 2026",
          "url": "https://www.eetimes.com/ee-times-magazine-june-2026/"
        }
      ]
    }
  ]
}