{
  "range": {
    "from": "2026-04-30",
    "to": "2026-05-29"
  },
  "kpis": {
    "collected": 72,
    "deduped": 72,
    "uniqueTopics": 9,
    "marketShare": {
      "MarketInfra": 35,
      "Policy": 26,
      "Regulation": 15,
      "Compliance": 14,
      "Fintech": 10,
      "Other": 0
    }
  },
  "weeklyData": [
    {
      "week": "Week 1 (04/30-05/06)",
      "topicCounts": {
        "MarketInfra": 12,
        "Policy": 9,
        "Regulation": 3,
        "Compliance": 3,
        "Fintech": 3
      }
    },
    {
      "week": "Week 2 (05/07-05/13)",
      "topicCounts": {
        "MarketInfra": 11,
        "Policy": 9,
        "Regulation": 5,
        "Compliance": 3,
        "Fintech": 1
      }
    },
    {
      "week": "Week 3 (05/14-05/20)",
      "topicCounts": {
        "MarketInfra": 13,
        "Policy": 12,
        "Regulation": 6,
        "Compliance": 8,
        "Fintech": 7
      }
    },
    {
      "week": "Week 4 (05/21-05/27)",
      "topicCounts": {
        "MarketInfra": 13,
        "Policy": 9,
        "Regulation": 6,
        "Compliance": 5,
        "Fintech": 5
      }
    },
    {
      "week": "Week 5 (05/28-05/29)",
      "topicCounts": {
        "MarketInfra": 3,
        "Policy": 3,
        "Regulation": 0,
        "Compliance": 1,
        "Fintech": 0
      }
    }
  ],
  "topIssues": [
    {
      "id": 1,
      "status": "ONGOING",
      "title": "코스피 급락과 대형주 변동성 확대",
      "summary": "국내외 악재가 겹치며 코스피가 장중 7800선까지 밀리는 등 변동성이 극단적으로 확대되고 있다. 기존에는 방어적 자산으로 여겨지던 대형주마저 개별 중소형주처럼 흔들리면서, ‘대장주 투자도 도박 같다’는 인식이 퍼질 정도로 투자심리가 위축된 상태다.",
      "articleCount": 1,
      "relatedArticles": [
        {
          "source": "매일경제(증권)",
          "title": "“대장주만 샀는데도 도박하는 느낌”…예측불가 코스피, 잡주처럼 ‘흔들’",
          "url": "https://www.mk.co.kr/news/stock/12060519"
        }
      ]
    },
    {
      "id": 2,
      "status": "SHIFTING",
      "title": "국민연금의 국내주식 비중 확대와 증시 영향",
      "summary": "국민연금이 올해 국내주식 목표 비중을 14.9%에서 20.8%로 크게 늘리기로 하면서, 중장기적으로 국내 증시 유동성 및 수급 개선 기대가 커지고 있다. 다만 구체적 집행 속도와 방식에 따라 업종·종목별 수혜가 달라질 수 있어 기관·개인 모두 전략 조정이 필요한 국면이다.",
      "articleCount": 1,
      "relatedArticles": [
        {
          "source": "매일경제(증권)",
          "title": "[속보] 국민연금, 올해 국내주식 목표 비중 14.9%→20.8%로 확대",
          "url": "https://www.mk.co.kr/news/economy/12060289"
        }
      ]
    },
    {
      "id": 3,
      "status": "ONGOING",
      "title": "중대 회계부정 상장사 신속 상장폐지 추진",
      "summary": "금융당국이 중대 회계부정을 저지른 상장사에 대해 포괄적 재량권을 부여해 신속 상장폐지를 가능하게 하는 제도 개편을 추진 중이다. 회계감리 강화, 계좌추적권 부여 등 집행 수단도 확대해 기존 2년가량 소요되던 퇴출 절차를 단축하려는 것으로, 코스피·코스닥 전반의 회계 투명성과 투자자 보호 강화가 핵심 목표다.",
      "articleCount": 1,
      "relatedArticles": [
        {
          "source": "매일경제(증권)",
          "title": "[단독] “썩은 살 도려내는 데 2년, 너무 길다”…중대 회계부정 상장사 즉각퇴출",
          "url": "https://www.mk.co.kr/news/stock/12057039"
        }
      ]
    },
    {
      "id": 4,
      "status": "ONGOING",
      "title": "삼성전자 소액주주 행동주의와 지배구조 이슈 부상",
      "summary": "삼성전자가 소액주주의 주주명부 열람·등사 청구를 수용하면서, 소액주주들의 임시주주총회 청구 등 주주행동주의 움직임이 본격화되고 있다. 이는 지배구조 개선, 배당·자사주 정책, IR 강화 등 대형 상장사의 주주권 이슈를 중장기 테마로 부각시킬 가능성이 크다.",
      "articleCount": 1,
      "relatedArticles": [
        {
          "source": "매일경제(증권)",
          "title": "[단독] 삼성전자, 주주명부 열람 수용…소액주주 임시주총 청구 본격화",
          "url": "https://www.mk.co.kr/news/stock/12056297"
        }
      ]
    },
    {
      "id": 5,
      "status": "ONGOING",
      "title": "미국 CLARITY 법안과 글로벌 가상자산 규제 재편",
      "summary": "미국의 클래리티법(CLARITY Act)이 암호자산의 법적 지위를 명확히 하려는 시도로 주목받고 있다. 법안 논의 과정에서 거래소와 주요 토큰 가격 변동성이 확대되고, 규제 준수 비용 증가가 관찰되는 등 글로벌 디지털자산 시장 구조와 국내 관련 업계에도 중장기 영향을 미칠 수 있는 규제 변화가 진행 중이다.",
      "articleCount": 1,
      "relatedArticles": [
        {
          "source": "매일경제(증권)",
          "title": "코인판 뒤흔드는 클래리티법(CLARITY Act)의 모든 것[엠블록레터]",
          "url": "https://www.mk.co.kr/news/stock/12053777"
        }
      ]
    }
  ]
}