{
  "range": {
    "from": "2026-03-27",
    "to": "2026-04-25"
  },
  "kpis": {
    "collected": 83,
    "deduped": 83,
    "uniqueTopics": 7,
    "marketShare": {
      "Roadmap": 28,
      "Competition": 26,
      "Manufacturing": 17,
      "Investment": 15,
      "Demand": 14,
      "Other": 0
    }
  },
  "weeklyData": [
    {
      "week": "Week 1 (03/27-04/02)",
      "topicCounts": {
        "Roadmap": 13,
        "Competition": 16,
        "Manufacturing": 7,
        "Investment": 8,
        "Demand": 10
      }
    },
    {
      "week": "Week 2 (04/03-04/09)",
      "topicCounts": {
        "Roadmap": 10,
        "Competition": 11,
        "Manufacturing": 8,
        "Investment": 5,
        "Demand": 2
      }
    },
    {
      "week": "Week 3 (04/10-04/16)",
      "topicCounts": {
        "Roadmap": 10,
        "Competition": 8,
        "Manufacturing": 9,
        "Investment": 4,
        "Demand": 3
      }
    },
    {
      "week": "Week 4 (04/17-04/23)",
      "topicCounts": {
        "Roadmap": 16,
        "Competition": 13,
        "Manufacturing": 7,
        "Investment": 8,
        "Demand": 7
      }
    },
    {
      "week": "Week 5 (04/24-04/25)",
      "topicCounts": {
        "Roadmap": 2,
        "Competition": 2,
        "Manufacturing": 2,
        "Investment": 2,
        "Demand": 1
      }
    }
  ],
  "topIssues": [
    {
      "id": "sem-1",
      "status": "NEW",
      "title": "AI 수요 폭증에 따른 메모리 반도체 슈퍼사이클 본격화",
      "summary": "SK하이닉스가 2026년 1분기 매출과 영업이익 모두 분기 사상 최대를 기록하며 AI용 고부가 메모리 수요가 실적으로 직결되고 있다. 이는 HBM·고용량 DDR 등 AI 인프라용 메모리 중심의 슈퍼사이클이 진행 중임을 보여주며, 설비·공정 고도화와 함께 향후 투자 확대 가능성을 높이고 있다.",
      "articleCount": 1,
      "relatedArticles": [
        {
          "source": "SK hynix Newsroom",
          "title": "SK hynix Announces 1Q26 Financial Results",
          "url": "https://news.skhynix.com/q1-2026-business-results/"
        }
      ]
    },
    {
      "id": "sem-2",
      "status": "NEW",
      "title": "청주 P&T7, 차세대 AI 메모리 패키징·테스트 거점으로 부상",
      "summary": "SK하이닉스가 청주 테크노폴리스 내 P&T7를 AI 메모리 생산 허브로 구축하며 M15X와 연계한 패키징·테스트 클러스터를 형성하고 있다. 이는 첨단 패키징 역량 내재화와 지역 경제 활성화를 동시에 겨냥한 투자로, AI 메모리 공급 능력 확대와 공급망 안정화에 기여할 전망이다.",
      "articleCount": 1,
      "relatedArticles": [
        {
          "source": "SK hynix Newsroom",
          "title": "What Does P&T7 Mean for Cheongju? A New AI Memory Production Hub and Catalyst for the Local Economy",
          "url": "https://news.skhynix.com/skhynix-chungju-pt7/"
        }
      ]
    },
    {
      "id": "sem-3",
      "status": "SHIFTING",
      "title": "반도체 공급망 리스크, 해상 운송·원자재 의존 구조가 핵심 취약점으로 부각",
      "summary": "호르무즈 사태를 계기로 해상 운송 경로와 단일 소스 원자재 의존이 반도체 공급망의 구조적 리스크로 재조명되고 있다. 물류 경로 다변화, 재고·소싱 전략 재편, 지역별 생산 거점 확대 등 제조·정책·투자 전반의 구조 개편 필요성이 커지고 있다.",
      "articleCount": 1,
      "relatedArticles": [
        {
          "source": "EE Times",
          "title": "What Hormuz Exposed About Our Semiconductor Supply Chain",
          "url": "https://www.eetimes.com/what-hormuz-exposed-about-our-semiconductor-supply-chain/"
        }
      ]
    },
    {
      "id": "sem-4",
      "status": "SHIFTING",
      "title": "칩 주권 경쟁, 단일 칩에서 시스템·소프트웨어·생태계 경쟁으로 확장",
      "summary": "각국과 주요 기업의 칩 주권 전략이 단순 제조 능력을 넘어 설계 IP, 시스템 통합, 소프트웨어, 보안, 생태계 구축 중심으로 재편되고 있다. 이는 파운드리·메모리뿐 아니라 패키징, EDA, OS·미들웨어 등 전 주기의 전략적 자립과 동맹 형성을 촉진하고 있다.",
      "articleCount": 1,
      "relatedArticles": [
        {
          "source": "EE Times",
          "title": "Why Chip Sovereignty Is No Longer About Chips—But Systems",
          "url": "https://www.eetimes.com/why-chip-sovereignty-is-no-longer-about-chips-but-systems/"
        }
      ]
    },
    {
      "id": "sem-5",
      "status": "SHIFTING",
      "title": "AI 인프라 확산에 대응한 통신·제조 자동화 투자 가속",
      "summary": "AI 트래픽 증가로 통신 장비와 인프라 비용 부담이 커지면서, 통신 업계는 네트워크 운영과 자원 할당을 소프트웨어 기반 자동화로 전환하고 있다. 이는 반도체·장비 업체에 고효율·저전력 솔루션 수요를 자극하며, 제조·운영 단계 전반의 자동화·최적화 투자를 촉진한다.",
      "articleCount": 1,
      "relatedArticles": [
        {
          "source": "EE Times",
          "title": "Telecom Industry Bets on Automation to Tackle AI Squeeze",
          "url": "https://www.eetimes.com/telecom-industry-bets-on-automation-to-tackle-ai-squeeze/"
        }
      ]
    }
  ]
}