{
  "range": {
    "from": "2026-06-24",
    "to": "2026-07-23"
  },
  "kpis": {
    "collected": 126,
    "deduped": 126,
    "uniqueTopics": 10,
    "marketShare": {
      "Market": 32,
      "Supply": 23,
      "Policy": 21,
      "Construction": 12,
      "Regulation": 12,
      "Other": 0
    }
  },
  "weeklyData": [
    {
      "week": "Week 1 (06/24-06/30)",
      "topicCounts": {
        "Market": 18,
        "Supply": 10,
        "Policy": 11,
        "Construction": 3,
        "Regulation": 5
      }
    },
    {
      "week": "Week 2 (07/01-07/07)",
      "topicCounts": {
        "Market": 25,
        "Supply": 12,
        "Policy": 13,
        "Construction": 10,
        "Regulation": 7
      }
    },
    {
      "week": "Week 3 (07/08-07/14)",
      "topicCounts": {
        "Market": 19,
        "Supply": 15,
        "Policy": 15,
        "Construction": 7,
        "Regulation": 9
      }
    },
    {
      "week": "Week 4 (07/15-07/21)",
      "topicCounts": {
        "Market": 21,
        "Supply": 18,
        "Policy": 11,
        "Construction": 11,
        "Regulation": 6
      }
    },
    {
      "week": "Week 5 (07/22-07/23)",
      "topicCounts": {
        "Market": 2,
        "Supply": 5,
        "Policy": 4,
        "Construction": 2,
        "Regulation": 2
      }
    }
  ],
  "topIssues": [
    {
      "id": "realestate-1",
      "status": "NEW",
      "title": "부동산 정책 국민 대토론회로 규제·세제·공급 전면 재점검",
      "summary": "정부가 부동산 정책 국민 대토론회를 열어 시민·전문가·관계자 의견을 한자리에서 수렴했다. 거래 규제, 세제, 공급 확대 등 전반에 대한 민심이 드러나 향후 정책 방향 조정의 분수령이 될 전망이다.",
      "articleCount": 2,
      "relatedArticles": [
        {
          "source": "한국경제(부동산)",
          "title": "오늘 부동산 정책 국민 대토론회…민심 톺아보니 [시장톡]",
          "url": "https://www.hankyung.com/article/2026072292406"
        },
        {
          "source": "한국경제(부동산)",
          "title": "\"거래 규제할수록 집값 폭등\"…부동산 토론회 불만 쏟아졌다",
          "url": "https://www.hankyung.com/article/2026072201291"
        }
      ]
    },
    {
      "id": "realestate-2",
      "status": "ONGOING",
      "title": "서울 준공업지·재개발을 활용한 도심 주택 공급 확대 논의",
      "summary": "서울 준공업지 일부만 주거·복합용으로 전환해도 수만 가구 공급이 가능하다는 분석과 함께, 영등포·구로 재개발·재건축 등 도심 정비사업 속도 조절·완화 방안이 논의되고 있다. 도심 내 유휴부지 활용과 정비사업 규제 조정이 핵심 이슈로 부상했다.",
      "articleCount": 2,
      "relatedArticles": [
        {
          "source": "매일경제(부동산)",
          "title": "서울 준공업지 20%만 풀어도…5만가구 공급 가능해진다",
          "url": "https://www.mk.co.kr/news/realestate/12105012"
        },
        {
          "source": "매일경제(부동산)",
          "title": "金 \"영등포·구로 재개발·재건축 속도내야 … 吳시장과 만날 것\"",
          "url": "https://www.mk.co.kr/news/realestate/12101841"
        }
      ]
    },
    {
      "id": "realestate-3",
      "status": "ONGOING",
      "title": "전세 매물 감소와 보증금 급등으로 확산되는 조기 전세계약",
      "summary": "서울 아파트 전세 매물 부족과 보증금 상승 압력 속에 세입자들이 입주 수개월 전부터 전세계약을 체결하는 비중이 크게 늘고 있다. 금천·관악 등 중저가 지역에서 조기 계약이 두드러지며 전세 시장 불안이 고착되는 양상이다.",
      "articleCount": 1,
      "relatedArticles": [
        {
          "source": "매일경제(부동산)",
          "title": "“자고 일어나면 전세값 올라요”…넉달전에 도장찍는 세입자들",
          "url": "https://www.mk.co.kr/news/realestate/12103823"
        }
      ]
    },
    {
      "id": "realestate-4",
      "status": "ONGOING",
      "title": "공사비·자금·규제에 막힌 주택 착공 급감과 공급 경고등",
      "summary": "전국 주택 착공 실적이 전년 대비 절반 수준으로 떨어지며 공급 절벽 우려가 커지고 있다. 공사비 상승, 자금 경색, 각종 규제, 토지 확보 난항, 지자체 민원 등 복합적인 장애 요인이 건설사들의 사업 추진 의지를 꺾고 있다는 분석이다.",
      "articleCount": 1,
      "relatedArticles": [
        {
          "source": "한국경제(부동산)",
          "title": "착공 '반토막'…5敵에 갇힌 주택공급",
          "url": "https://www.hankyung.com/article/2026071929201"
        }
      ]
    },
    {
      "id": "realestate-5",
      "status": "ONGOING",
      "title": "더블생활권·경계 입지 등 새로운 지방 주거 상품 수요 부상",
      "summary": "부산 대연·문현 일대에 공급되는 포스코이앤씨 '더샵 트리센트'처럼 두 개 이상의 생활권을 동시에 누리는 경계 입지 단지가 지방에서도 관심을 끌고 있다. 실수요자 위주의 입지 선호 변화가 지방 분양 시장 트렌드를 재편하는 양상이다.",
      "articleCount": 1,
      "relatedArticles": [
        {
          "source": "헤럴드경제(부동산)",
          "title": "‘더블생활권’ 갖춘 포스코이앤씨 ‘더샵 트리센트’, 부산 대연·문현서 공급",
          "url": "https://biz.heraldcorp.com/article/10813774"
        }
      ]
    }
  ]
}