{
  "range": {
    "from": "2026-06-17",
    "to": "2026-07-16"
  },
  "kpis": {
    "collected": 123,
    "deduped": 123,
    "uniqueTopics": 10,
    "marketShare": {
      "Market": 33,
      "Supply": 23,
      "Policy": 19,
      "Construction": 13,
      "Regulation": 12,
      "Other": 0
    }
  },
  "weeklyData": [
    {
      "week": "Week 1 (06/17-06/23)",
      "topicCounts": {
        "Market": 20,
        "Supply": 18,
        "Policy": 8,
        "Construction": 14,
        "Regulation": 7
      }
    },
    {
      "week": "Week 2 (06/24-06/30)",
      "topicCounts": {
        "Market": 18,
        "Supply": 10,
        "Policy": 11,
        "Construction": 3,
        "Regulation": 5
      }
    },
    {
      "week": "Week 3 (07/01-07/07)",
      "topicCounts": {
        "Market": 25,
        "Supply": 12,
        "Policy": 13,
        "Construction": 10,
        "Regulation": 7
      }
    },
    {
      "week": "Week 4 (07/08-07/14)",
      "topicCounts": {
        "Market": 19,
        "Supply": 15,
        "Policy": 15,
        "Construction": 7,
        "Regulation": 9
      }
    },
    {
      "week": "Week 5 (07/15-07/16)",
      "topicCounts": {
        "Market": 4,
        "Supply": 2,
        "Policy": 3,
        "Construction": 1,
        "Regulation": 2
      }
    }
  ],
  "topIssues": [
    {
      "id": 1,
      "status": "ONGOING",
      "title": "강남3구 분양가 3.3㎡당 8000만원 육박…건축비 상승에 분양가 규제 효과 약화",
      "summary": "철근 등 원자재 가격 급등으로 기본형건축비가 인상되면서 강남3구 신규 분양가가 3.3㎡당 8000만원에 근접하고, 서울 전체 평균 분양가도 6000만원 돌파를 앞두는 등 분양가 상한제의 실질적인 제어력이 약해지고 있다.",
      "articleCount": 2,
      "relatedArticles": [
        {
          "source": "매일경제(부동산)",
          "title": "강남3구 분양가 8000만원 육박 … 건축비 폭등에 분상제 힘빠져",
          "url": "https://www.mk.co.kr/news/realestate/12099511"
        },
        {
          "source": "헤럴드경제(부동산)",
          "title": "“강남 분양가 더 오르겠네” ‘분상제 적용’ 기본형건축비 ㎡당 1.7만원 상승 [부동산360]",
          "url": "https://biz.heraldcorp.com/article/10808571"
        }
      ]
    },
    {
      "id": 2,
      "status": "ONGOING",
      "title": "분양 공고 규제 강화로 분양 현장 리스크 확대",
      "summary": "교육환경보호구역 표기 누락 사례처럼 분양 공고의 사소한 기재 오류도 계약 취소와 행정조치로 이어질 수 있다는 우려가 커지면서, 오피스텔을 포함한 분양 현장에서 규제 리스크 관리와 심사가 한층 엄격해지는 분위기다.",
      "articleCount": 1,
      "relatedArticles": [
        {
          "source": "매일경제(부동산)",
          "title": "\"경미한 위반도 계약취소\"… 분양현장 비상",
          "url": "https://www.mk.co.kr/news/realestate/12099430"
        }
      ]
    },
    {
      "id": 3,
      "status": "ONGOING",
      "title": "서울 전세 물량 급감과 집값·전셋값 동시 급등",
      "summary": "서울시 토지거래허가 대장 4.4만건 분석에서 1년 새 전세가 30% 줄었다는 발표와 함께, 서울 아파트 매매가격과 전셋값이 모두 월 1% 이상 뛰는 등 전세 공급 부족과 집값 동반 상승으로 실수요자의 부담이 급격히 커지고 있다.",
      "articleCount": 2,
      "relatedArticles": [
        {
          "source": "헤럴드경제(부동산)",
          "title": "“1년 새 전세 30% 줄어” 오세훈, 토허대장 4.4만건 분석 후 ‘부동산 지옥’ [부동산360]",
          "url": "https://biz.heraldcorp.com/article/10810094"
        },
        {
          "source": "헤럴드경제(부동산)",
          "title": "“성북동 아파트 1년 새 5억 올랐다” 서울 집값도 전셋값도 최대폭 상승 [부동산360]",
          "url": "https://biz.heraldcorp.com/article/10809620"
        }
      ]
    },
    {
      "id": 4,
      "status": "ONGOING",
      "title": "재개발·재건축 이주비 대출 규제 완화 요구 확산",
      "summary": "서울시 공무원들이 국토부 토론회에서 재개발·재건축 추진 단지의 이주비 대출 LTV를 70%까지 완화해야 한다고 제안하는 등, 사업 추진 속도를 높이기 위해 이주비 금융 규제 완화를 요구하는 목소리가 커지고 있다.",
      "articleCount": 1,
      "relatedArticles": [
        {
          "source": "한국경제(부동산)",
          "title": "국토부 토론회서 서울시 공무원들 \"이주비 대출 LTV 70%로 풀어줘야\"",
          "url": "https://www.hankyung.com/article/202607156557i"
        }
      ]
    },
    {
      "id": 5,
      "status": "ONGOING",
      "title": "서울 모아타운 규제 완화로 소규모 정비·주택공급 확대 추진",
      "summary": "서울시가 모아타운 사업의 노후 불량 건축물 동의 요건 등 자문·심사 기준을 완화해 진입 장벽을 낮추고, 노후 저층 주거지 정비와 공급 속도를 동시에 끌어올리려는 소규모 정비사업 활성화 정책을 강화하고 있다.",
      "articleCount": 1,
      "relatedArticles": [
        {
          "source": "매일경제(부동산)",
          "title": "[단독]‘닥공’ 서울시…모아타운 문턱 낮춘다",
          "url": "https://www.mk.co.kr/news/realestate/12098640"
        }
      ]
    }
  ]
}