{
  "range": {
    "from": "2026-02-22",
    "to": "2026-02-28"
  },
  "kpis": {
    "collected": 22,
    "deduped": 22,
    "uniqueTopics": 9
  },
  "topTopics": [
    {
      "name": "Policy",
      "count": 19
    },
    {
      "name": "MarketInfra",
      "count": 18
    },
    {
      "name": "Fintech",
      "count": 8
    },
    {
      "name": "Regulation",
      "count": 8
    }
  ],
  "topicTrend": [
    {
      "date": "2026-02-22",
      "dayOfWeek": "Sun",
      "topic": "Policy",
      "count": 1
    },
    {
      "date": "2026-02-22",
      "dayOfWeek": "Sun",
      "topic": "MarketInfra",
      "count": 1
    },
    {
      "date": "2026-02-22",
      "dayOfWeek": "Sun",
      "topic": "Fintech",
      "count": 0
    },
    {
      "date": "2026-02-22",
      "dayOfWeek": "Sun",
      "topic": "Regulation",
      "count": 1
    },
    {
      "date": "2026-02-23",
      "dayOfWeek": "Mon",
      "topic": "Policy",
      "count": 3
    },
    {
      "date": "2026-02-23",
      "dayOfWeek": "Mon",
      "topic": "MarketInfra",
      "count": 2
    },
    {
      "date": "2026-02-23",
      "dayOfWeek": "Mon",
      "topic": "Fintech",
      "count": 1
    },
    {
      "date": "2026-02-23",
      "dayOfWeek": "Mon",
      "topic": "Regulation",
      "count": 2
    },
    {
      "date": "2026-02-24",
      "dayOfWeek": "Tue",
      "topic": "Policy",
      "count": 2
    },
    {
      "date": "2026-02-24",
      "dayOfWeek": "Tue",
      "topic": "MarketInfra",
      "count": 4
    },
    {
      "date": "2026-02-24",
      "dayOfWeek": "Tue",
      "topic": "Fintech",
      "count": 3
    },
    {
      "date": "2026-02-24",
      "dayOfWeek": "Tue",
      "topic": "Regulation",
      "count": 0
    },
    {
      "date": "2026-02-25",
      "dayOfWeek": "Wed",
      "topic": "Policy",
      "count": 6
    },
    {
      "date": "2026-02-25",
      "dayOfWeek": "Wed",
      "topic": "MarketInfra",
      "count": 5
    },
    {
      "date": "2026-02-25",
      "dayOfWeek": "Wed",
      "topic": "Fintech",
      "count": 0
    },
    {
      "date": "2026-02-25",
      "dayOfWeek": "Wed",
      "topic": "Regulation",
      "count": 2
    },
    {
      "date": "2026-02-26",
      "dayOfWeek": "Thu",
      "topic": "Policy",
      "count": 3
    },
    {
      "date": "2026-02-26",
      "dayOfWeek": "Thu",
      "topic": "MarketInfra",
      "count": 2
    },
    {
      "date": "2026-02-26",
      "dayOfWeek": "Thu",
      "topic": "Fintech",
      "count": 1
    },
    {
      "date": "2026-02-26",
      "dayOfWeek": "Thu",
      "topic": "Regulation",
      "count": 1
    },
    {
      "date": "2026-02-27",
      "dayOfWeek": "Fri",
      "topic": "Policy",
      "count": 4
    },
    {
      "date": "2026-02-27",
      "dayOfWeek": "Fri",
      "topic": "MarketInfra",
      "count": 4
    },
    {
      "date": "2026-02-27",
      "dayOfWeek": "Fri",
      "topic": "Fintech",
      "count": 3
    },
    {
      "date": "2026-02-27",
      "dayOfWeek": "Fri",
      "topic": "Regulation",
      "count": 2
    },
    {
      "date": "2026-02-28",
      "dayOfWeek": "Sat",
      "topic": "Policy",
      "count": 0
    },
    {
      "date": "2026-02-28",
      "dayOfWeek": "Sat",
      "topic": "MarketInfra",
      "count": 0
    },
    {
      "date": "2026-02-28",
      "dayOfWeek": "Sat",
      "topic": "Fintech",
      "count": 0
    },
    {
      "date": "2026-02-28",
      "dayOfWeek": "Sat",
      "topic": "Regulation",
      "count": 0
    }
  ],
  "topIssues": [
    {
      "id": "finance-1",
      "status": "ONGOING",
      "title": "한국 증시 오전 7시 개장·12시간 거래 추진",
      "summary": "한국거래소가 오전 7시 개장과 12시간 거래 등 거래시간 대폭 연장을 추진하고 있으며, 국내외 증권사 27곳이 찬성 의사를 밝히며 제도 변경 가능성이 커지고 있다. 이는 개인·외국인 거래 패턴과 파생·야간선물 연계, 시스템 투자전략 등에 중대한 영향을 줄 수 있는 인프라 이슈다.",
      "articleCount": 1,
      "relatedArticles": [
        {
          "source": "매일경제(증권)",
          "title": "[단독] “불장에 더 먹어야 해”…아침 7시 증시개장에 증권사 27곳 ‘찬성’",
          "url": "https://www.mk.co.kr/news/stock/11974910"
        }
      ]
    },
    {
      "id": "finance-2",
      "status": "ONGOING",
      "title": "ISA 계좌 투자 급증과 절세형 개인투자 확대",
      "summary": "한 달 새 ISA(개인종합자산관리계좌) 가입자가 42만명 늘며 800만명을 돌파했다. 신규 가입자의 약 87%가 투자중개형(직접 운용)을 선택하고, 그 중 80%가 ETF·주식 투자에 나서면서 세제 혜택을 활용한 직접투자 자금 유입이 빠르게 확대되고 있다.",
      "articleCount": 1,
      "relatedArticles": [
        {
          "source": "매일경제(증권)",
          "title": "“이왕 주식할거면 절세혜택도 챙겨야”…ISA가입 한달새 42만명 급증",
          "url": "https://www.mk.co.kr/news/stock/11973998"
        }
      ]
    },
    {
      "id": "finance-3",
      "status": "ONGOING",
      "title": "증권주 랠리와 밸류에이션 과열 논쟁",
      "summary": "이달 들어 증권지수가 40% 이상 급등하며 증권주가 신고가 행진을 이어가고 있다. 일부 종목이 투자주의·단기과열로 지정되는 등 과열 신호가 나타나는 가운데, 거래대금 증가와 이자이익 확대 기대를 반영한 상승이 어디까지 이어질지에 대한 시장 평가가 엇갈리고 있다.",
      "articleCount": 1,
      "relatedArticles": [
        {
          "source": "매일경제(증권)",
          "title": "“증권株 지금 담아도 안 늦었나요?”…신고가 행진 시장의 평가는",
          "url": "https://www.mk.co.kr/news/stock/11968556"
        }
      ]
    },
    {
      "id": "finance-4",
      "status": "ONGOING",
      "title": "국민연금 사상 최대 수익률과 장기 기금 운용력 부각",
      "summary": "국민연금이 2023년 수익률 18.82%를 기록하며 약 231조원의 이익을 거뒀고, 이는 1988년 기금 설립 이후 최고 성과다. 국내외 주식 및 대체투자 성과가 동시에 개선되면서 기금 고갈 논쟁과 함께 향후 자산배분 전략 및 책임투자 방향에 대한 관심이 커지고 있다.",
      "articleCount": 1,
      "relatedArticles": [
        {
          "source": "매일경제(증권)",
          "title": "'갓스피' 덕에 … 국민연금 작년 231조 벌었다",
          "url": "https://www.mk.co.kr/news/stock/11974889"
        }
      ]
    },
    {
      "id": "finance-5",
      "status": "ONGOING",
      "title": "새출발기금 인센티브 확대와 소상공인·자영업 부채 구조조정",
      "summary": "새출발기금이 소상공인·자영업자의 조기·성실상환 시 원금 5~10% 추가 감면과 금리 추가 인하를 제공하는 인센티브를 도입한다. 출산·육아휴직, 중증장애·중증질환 부양 등 다양한 사유에 대한 상환 유예 기준을 확대하고 긴급 상환유예 제도도 신설해 코로나 이후 과중 채무의 연착륙을 지원하고 있다.",
      "articleCount": 1,
      "relatedArticles": [
        {
          "source": "정책브리핑",
          "title": "새출발기금 성실상환 인센티브 강화…조기상환시 5~10% 추가 감면",
          "url": "https://www.korea.kr/news/policyNewsView.do?newsId=148960086&call_from=rsslink"
        }
      ]
    }
  ]
}