{
  "date": "2026-06-10",
  "highlights": {
    "bullets": [
      "핵심: 중국에서 5월 판매된 상위 16개 차량이 모두 전기차였고 내연기관 판매가 구조적 하락을 지속한다",
      "핵심: GM이 Redwood와 배터리 전 생애주기 파트너십을 확장하고 미시간에 1.5MW/7.2MWh 에너지 저장 시스템을 설치할 예정이다"
    ],
    "topTopics": [
      "Roadmap",
      "Competition",
      "Demand",
      "Investment"
    ],
    "stats": {
      "collected": 15,
      "deduped": 15
    }
  },
  "cards": [
    {
      "id": "ev_0001",
      "tab": "ev",
      "publishedAt": "2026-06-09T21:00:00+09:00",
      "source": "Electrek",
      "title": "ICE car sales continue to plummet in China, the top 16 cars are now electric",
      "summary": [
        "중국에서 5월 판매된 상위 16개 차량은 모두 전기차였다.",
        "내연기관 차량(ICE)의 판매가 구조적 하락을 지속하고 있다.",
        "세계 최대 자동차 시장에서 전기차 중심으로 시장 구도가 빠르게 재편되고 있다."
      ],
      "whyItMatters": "소비자 수요와 제조·경쟁 구도가 전기차로 빠르게 이동하면서 ICE 수요가 급감하고 있기 때문이다.",
      "topics": [
        "Demand",
        "Competition",
        "Manufacturing"
      ],
      "status": "SHIFTING",
      "hash": "53672f876e7d2d8d0a7971aaed2f652ba924fdb186f49836bbfb29d89aa4112d",
      "url": "https://electrek.co/2026/06/09/ice-car-sales-continue-to-plummet-in-china-the-top-16-cars-are-now-evs/"
    },
    {
      "id": "ev_0002",
      "tab": "ev",
      "publishedAt": "2026-06-10T06:52:35+09:00",
      "source": "Electrek",
      "title": "GM becomes first automaker to partner with Redwood across full battery lifecycle",
      "summary": [
        "GM은 Redwood Materials와의 파트너십을 배터리 전 생애주기(스크랩 회수, 사용후 재활용, 세컨드라이프 에너지 저장)로 확장했습니다.",
        "GM은 약 100개의 재사용 배터리 팩으로 구성된 1.5MW / 7.2MWh 에너지 저장 시스템을 미시간 공장에 설치할 예정입니다.",
        "이 시스템은 공장 전기료를 수명 기간 동안 300만 달러 이상 절감할 것으로 예상됩니다."
      ],
      "whyItMatters": "완성차 업체가 배터리 재사용·재활용을 제조공정까지 통합한 첫 사례로, 전기차 배터리 가치사슬과 비용 구조, 향후 경쟁사의 전략에 중대한 영향을 줄 수 있습니다.",
      "topics": [
        "Manufacturing",
        "Investment",
        "Roadmap",
        "Competition"
      ],
      "status": "NEW",
      "hash": "9bf7db96b48961d5d1c7efbd3c81618602ac2be372e5adb76322d85db30537b4",
      "url": "https://electrek.co/2026/06/09/gm-first-automaker-redwood-materials-full-battery-lifecycle/"
    }
  ]
}