{
  "range": {
    "from": "2026-04-06",
    "to": "2026-05-05"
  },
  "kpis": {
    "collected": 135,
    "deduped": 135,
    "uniqueTopics": 10,
    "marketShare": {
      "Market": 34,
      "Supply": 26,
      "Policy": 18,
      "Regulation": 12,
      "Construction": 11,
      "Other": 0
    }
  },
  "weeklyData": [
    {
      "week": "Week 1 (04/06-04/12)",
      "topicCounts": {
        "Market": 25,
        "Supply": 19,
        "Policy": 19,
        "Regulation": 9,
        "Construction": 10
      }
    },
    {
      "week": "Week 2 (04/13-04/19)",
      "topicCounts": {
        "Market": 28,
        "Supply": 20,
        "Policy": 13,
        "Regulation": 9,
        "Construction": 6
      }
    },
    {
      "week": "Week 3 (04/20-04/26)",
      "topicCounts": {
        "Market": 26,
        "Supply": 19,
        "Policy": 11,
        "Regulation": 9,
        "Construction": 10
      }
    },
    {
      "week": "Week 4 (04/27-05/03)",
      "topicCounts": {
        "Market": 22,
        "Supply": 21,
        "Policy": 11,
        "Regulation": 9,
        "Construction": 10
      }
    },
    {
      "week": "Week 5 (05/04-05/05)",
      "topicCounts": {
        "Market": 4,
        "Supply": 3,
        "Policy": 1,
        "Regulation": 2,
        "Construction": 0
      }
    }
  ],
  "topIssues": [
    {
      "id": 1,
      "status": "SHIFTING",
      "title": "서울 토지거래허가 1만건 돌파…다주택 매물 ‘막차’ 흡수 가속",
      "summary": "서울 토지거래허가 신청이 1만건을 넘기며 규제·세 부담을 의식한 시장 참여자들의 ‘막차 수요’가 강하게 표출되고 있다. 특히 현금 보유 무주택자들이 다주택자 매물을 공격적으로 흡수하면서 토지·주택 매물 소화 속도가 빨라지고, 향후 거래 규제·중과 강화 국면을 앞둔 선제 매수 흐름이 뚜렷해지는 것이 이번 주의 핵심 이슈다.",
      "articleCount": 1,
      "relatedArticles": [
        {
          "source": "매일경제(부동산)",
          "title": "“막차 놓칠라” 다주택 매물 다 주워간다…서울 토허신청 1만건",
          "url": "https://www.mk.co.kr/news/realestate/12035771"
        }
      ]
    },
    {
      "id": 2,
      "status": "ONGOING",
      "title": "서울·수도권 전세시장 양극화와 풍선효과 심화",
      "summary": "서울에서는 같은 단지·같은 평형에서도 전세 보증금이 최대 11억원까지 벌어지는 ‘이중가격’ 현상이 이어지고, 서울 전셋집 부족으로 수요가 경기권으로 이동해 안양·수원·용인 등에서 전세와 매매가격이 동반 상승하고 있다. 서울 내부 전세 가격 왜곡과 함께 외곽·경기권으로의 수요 분산이 동시에 진행되며 수도권 전반의 전월세 불안이 중장기 이슈로 굳어지는 흐름이다.",
      "articleCount": 2,
      "relatedArticles": [
        {
          "source": "한국경제(부동산)",
          "title": "서울 전세 '이중가격'…같은 단지·같은 평형서 11억원 차이",
          "url": "https://www.hankyung.com/article/202605045650i"
        },
        {
          "source": "매일경제(부동산)",
          "title": "“전셋집 없어 서울 떠납니다”…풍선효과에 경기 전세·집값 동반 상승",
          "url": "https://www.mk.co.kr/news/realestate/12034069"
        }
      ]
    },
    {
      "id": 3,
      "status": "ONGOING",
      "title": "부동산 대출·청약 규제 동시 강화…‘실수요 중심’ 정책기조 고착",
      "summary": "청와대·정부가 실수요와 무관한 부동산 대출은 앞으로 차단하겠다는 의지를 공개적으로 밝히고, 국토부가 부양가족 청약 가점 인정 기준을 ‘1년 동거’에서 ‘3년 동거’로 강화하는 등 대출·청약 영역 전반에서 투기·편법 수요를 정조준한 규제가 동시다발적으로 추진되고 있다. 실수요자 중심 공급·금융 원칙이 재확인되면서 단기 투자 수요 위축과 청약 전략 재조정이 불가피한 상황이다.",
      "articleCount": 2,
      "relatedArticles": [
        {
          "source": "매일경제(부동산)",
          "title": "김용범 “실수요와 무관한 대출, 앞으로 못 나가게 하는 것 당연”",
          "url": "https://www.mk.co.kr/news/politics/12035436"
        },
        {
          "source": "매일경제(부동산)",
          "title": "출가한 자식이 부양가족?…3년 함께 살아야 청약점수 인정됩니다",
          "url": "https://www.mk.co.kr/news/realestate/12031805"
        }
      ]
    },
    {
      "id": 4,
      "status": "ONGOING",
      "title": "양도소득세 확정신고·납부 집중기…부동산 거래 투명성 제고",
      "summary": "국세청이 지난해 양도소득 발생자 22만명을 대상으로 6월 1일까지 양도소득세 확정신고·납부를 안내하고, 전자신고·미리채움 서비스와 오류사례 안내 등을 확대하고 있다. 납부세액 1000만원 초과 시 분납을 허용하는 한편 탈루에 대해서는 예외 없이 추징하겠다는 방침으로, 부동산 양도세 실무 부담은 낮추면서도 탈세·축소신고에 대한 관리 강도가 높아지는 점이 이번 기간의 핵심 포인트다.",
      "articleCount": 1,
      "relatedArticles": [
        {
          "source": "정책브리핑",
          "title": "6월 1일까지 '양도소득세 신고·납부'…탈루 예외 없이 추징",
          "url": "https://www.korea.kr/news/policyNewsView.do?newsId=148963850&call_from=rsslink"
        }
      ]
    },
    {
      "id": 5,
      "status": "ONGOING",
      "title": "서울 강북 재건축 본격 시동…노후 대단지 정비 가속",
      "summary": "상계에 이어 중계·하계 등 서울 강북 권역 전반으로 재건축 추진이 확산되고 있다. 서울시가 지난해 수립한 재건축 마스터플랜을 토대로 노후 아파트 단지 정비가 속도를 내면서, 강북의 주거환경 개선과 공급 확대 기대감이 동반 상승하고 있다. 다만 안전진단·사업성·규제 변수에 따라 속도 차가 벌어질 가능성도 커 단지별 옥석 가리기가 심화되는 국면이다.",
      "articleCount": 1,
      "relatedArticles": [
        {
          "source": "매일경제(부동산)",
          "title": "강북에 부는 재건축 바람 … 상계 이어 중계·하계도 시동",
          "url": "https://www.mk.co.kr/news/realestate/12034515"
        }
      ]
    }
  ]
}