{
  "date": "2026-05-05",
  "highlights": {
    "bullets": [
      "핵심: 서울 아파트 월세 비중이 절반에 달해 서민의 주거비 부담이 커지고 있다.",
      "핵심: 서울에서 토지거래허가 신청이 1만건을 넘어 거래 패턴 변화와 매물 흡수가 관측됐다.",
      "트렌드: 부동산 시장에서는 규제 강화와 주거 불안 신호가 공통적으로 나타나고 있다."
    ],
    "topTopics": [
      "Market",
      "Rental",
      "Supply",
      "Regulation"
    ],
    "stats": {
      "collected": 13,
      "deduped": 10
    }
  },
  "cards": [
    {
      "id": "realestate_0001",
      "tab": "realestate",
      "publishedAt": "2026-05-04T17:24:28+09:00",
      "source": "한국경제(부동산)",
      "title": "서울 아파트 월세 비중 50%, 서민 주거여건 갈수록 팍팍",
      "summary": [
        "서울 아파트 월세 비중이 절반에 달했다.",
        "월세 중심의 주거구조가 서민들의 주거비 부담을 키우고 있다.",
        "임대시장 불안과 공급 부족이 주거여건 악화로 이어지고 있다."
      ],
      "whyItMatters": "월세 비중 증가는 서민 가계부담과 주거 불안정 확대를 의미해 긴급한 공급·정책 대응을 요구한다.",
      "topics": [
        "Rental",
        "Market",
        "Supply",
        "UrbanRenewal"
      ],
      "status": "ONGOING",
      "hash": "87c6f04f651fdac77bf7ed30b010e5d498436055013187fdcd882f346ce42e9f",
      "url": "https://www.hankyung.com/article/2026050453601"
    },
    {
      "id": "realestate_0002",
      "tab": "realestate",
      "publishedAt": "2026-05-05T05:48:10+09:00",
      "source": "매일경제(부동산)",
      "title": "“막차 놓칠라” 다주택 매물 다 주워간다…서울 토허신청 1만건",
      "summary": [
        "서울에서 토지거래허가 신청 건수가 1만건을 넘겼다.",
        "임박한 규제·중과를 피하려는 현금 보유 무주택자들이 다주택 매물을 급히 흡수하고 있다.",
        "매물 감소로 허가 시행 이후 서울 부동산의 가격 상승 압력이 커질 가능성이 높다."
      ],
      "whyItMatters": "토지거래허가 급증은 규제·세제 변화가 거래 패턴과 공급을 급격히 바꿔 시장 불안과 가격 영향력을 키우기 때문입니다.",
      "topics": [
        "Land",
        "Market",
        "Regulation",
        "Supply"
      ],
      "status": "SHIFTING",
      "hash": "aea025bf379f789e9bc4923e754b157c22d8a74877e573688d75ee58c1a5fa4d",
      "url": "https://www.mk.co.kr/news/realestate/12035771"
    },
    {
      "id": "realestate_0003",
      "tab": "realestate",
      "publishedAt": "2026-05-04T20:05:15+09:00",
      "source": "한국경제(부동산)",
      "title": "서울 전세 '이중가격'…같은 단지·같은 평형서 11억원 차이",
      "summary": [
        "서울 일부 단지에서 같은 평형의 전세가가 최대 11억원까지 차이난다.",
        "계약 시점·층·향·집주인 사정 등으로 동일 단지 내 가격이 크게 엇갈리는 것으로 보인다.",
        "임차인의 주거비 부담과 시장 불투명성이 심화돼 정책적 대응 필요성이 커지고 있다."
      ],
      "whyItMatters": "이 현상은 전세 시장의 공급·수요 불균형과 정보 비대칭을 드러내며 주거안정과 정책 대응을 요구한다.",
      "topics": [
        "Rental",
        "Market",
        "Supply"
      ],
      "status": "ONGOING",
      "hash": "94f6d41a70751d02d630c2900692c930d91059780b25b32a46b265b36af12e63",
      "url": "https://www.hankyung.com/article/202605045650i"
    },
    {
      "id": "realestate_0004",
      "tab": "realestate",
      "publishedAt": "2026-05-04T19:25:51+09:00",
      "source": "매일경제(부동산)",
      "title": "김용범 “실수요와 무관한 대출, 앞으로 못 나가게 하는 것 당연”",
      "summary": [
        "김용범 청와대 정책실장은 실수요와 무관한 대출을 앞으로 막는 것이 당연하다고 밝혔다.",
        "이번 발언은 부동산 대출 규제 강화 의지를 명확히 한 것이라는 신호다.",
        "실수요자 보호와 시장 안정화를 위한 대출 심사·규제 강화가 예상된다."
      ],
      "whyItMatters": "정부가 투기성·비실수요 대출을 차단해 시장 안정과 실수요자 보호를 도모하려는 목적이다.",
      "topics": [
        "Policy",
        "Regulation",
        "Mortgage"
      ],
      "status": "ONGOING",
      "hash": "ade2f206905b4ae3b98756519afba93d997bf0ada6abd41a48b0ccb7537b7a3d",
      "url": "https://www.mk.co.kr/news/politics/12035436"
    },
    {
      "id": "realestate_0005",
      "tab": "realestate",
      "publishedAt": "2026-05-04T16:27:00+09:00",
      "source": "정책브리핑",
      "title": "6월 1일까지 '양도소득세 신고·납부'…탈루 예외 없이 추징",
      "summary": [
        "국세청이 지난해 양도소득 발생자 22만 명을 대상으로 6월 1일까지 양도소득세 확정신고·납부를 안내하고 전자신고 지원과 미리채움 서비스 등을 확대했다.",
        "납부세액 1000만 원 초과 시 분납을 허용하고, 다양한 신고 가이드·동영상·오류사례 제공으로 고령자와 일반 납세자의 신고 편의를 높였다.",
        "다운계약서·허위 필요경비·편법 특수관계자 거래 등 탈루 거래에 대해 관계기관과 공조해 실거래·자금흐름을 분석하고 예외 없이 추징 및 강도 높은 세무조사를 예고했다."
      ],
      "whyItMatters": "부동산·주식 등 자산 거래에 대한 양도소득세 신고를 강화하고 탈루에 대한 추징을 예고함으로써 시장의 투명성과 조세 부담 체계를 크게 변화시킬 수 있는 조치이기 때문이다.",
      "topics": [
        "Tax",
        "Market",
        "Land"
      ],
      "status": "ONGOING",
      "hash": "521ee6c5ff6cc3f61d79023984dec682f8abdae5590ccec55c05b0bff7970077",
      "url": "https://www.korea.kr/news/policyNewsView.do?newsId=148963850&call_from=rsslink"
    }
  ]
}