{
  "range": {
    "from": "2026-01-08",
    "to": "2026-02-06"
  },
  "kpis": {
    "collected": 30,
    "deduped": 30,
    "uniqueTopics": 7,
    "marketShare": {
      "Roadmap": 30,
      "Competition": 25,
      "Manufacturing": 17,
      "Investment": 17,
      "Demand": 12,
      "Other": 0
    }
  },
  "weeklyData": [
    {
      "week": "Week 1 (01/08-01/14)",
      "topicCounts": {
        "Roadmap": 0,
        "Competition": 0,
        "Manufacturing": 0,
        "Investment": 0,
        "Demand": 0
      }
    },
    {
      "week": "Week 2 (01/15-01/21)",
      "topicCounts": {
        "Roadmap": 0,
        "Competition": 0,
        "Manufacturing": 0,
        "Investment": 0,
        "Demand": 0
      }
    },
    {
      "week": "Week 3 (01/22-01/28)",
      "topicCounts": {
        "Roadmap": 3,
        "Competition": 2,
        "Manufacturing": 1,
        "Investment": 2,
        "Demand": 1
      }
    },
    {
      "week": "Week 4 (01/29-02/04)",
      "topicCounts": {
        "Roadmap": 12,
        "Competition": 8,
        "Manufacturing": 8,
        "Investment": 5,
        "Demand": 4
      }
    },
    {
      "week": "Week 5 (02/05-02/06)",
      "topicCounts": {
        "Roadmap": 2,
        "Competition": 2,
        "Manufacturing": 3,
        "Investment": 2,
        "Demand": 1
      }
    }
  ],
  "topIssues": [
    {
      "id": 1,
      "status": "ONGOING",
      "title": "인텔 18A 공정·Panther Lake: 미·우방 중심 첨단 공정 재편",
      "summary": "인텔이 차세대 Panther Lake를 자사 18A 공정에서 생산하려는 전략은 파운드리 경쟁력 회복과 동시에 미국 및 동맹국 중심으로 첨단 공정 생산을 재배치하려는 지정학적 흐름을 반영한다. 이는 첨단 반도체 공급망에서 미·중 기술 블록화와 우방 간 공급 다변화가 중장기 구조로 굳어지는 신호로 해석된다.",
      "articleCount": 1,
      "relatedArticles": [
        {
          "source": "TechInsights",
          "title": "Intel Panther Lake on Intel 18A: Strategic & Geopolitical Analysis",
          "url": "https://www.techinsights.com/blog/intel-panther-lake-intel-18a-strategic-geopolitical-analysis"
        }
      ]
    },
    {
      "id": 2,
      "status": "NEW",
      "title": "TI의 실리콘랩스 인수: IoT·엣지 AI용 반도체 포트폴리오 통합",
      "summary": "TI가 실리콘랩스를 인수하며 무선 연결, MCU, 보안 솔루션을 자사 제품 로드맵에 통합해 IoT·엣지 AI용 반도체 플랫폼을 수직적으로 강화하고 있다. 아날로그·전력 반도체 강자인 TI가 커넥티비티와 임베디드 분야까지 확장함에 따라 IoT·산업용 반도체 시장 경쟁 구도가 재편될 가능성이 크다.",
      "articleCount": 1,
      "relatedArticles": [
        {
          "source": "EE Times",
          "title": "What TI’s Acquisition of Silicon Labs Stands For?",
          "url": "https://www.eetimes.com/what-ti-acquisition-of-silicon-labs-stands-for/"
        }
      ]
    },
    {
      "id": 3,
      "status": "SHIFTING",
      "title": "유럽 디지털 주권 논쟁: 클라우드·반도체 인프라 자립 요구 증폭",
      "summary": "HiPEAC 2026에서 미국 클라우드 의존과 데이터 통제 문제를 계기로 유럽의 디지털 주권과 인프라 자립 요구가 커지고 있다. 이는 향후 유럽 내 데이터센터, AI·고성능 컴퓨팅용 반도체, 설계·제조 생태계에 대한 투자와 규제 정책을 강화하는 방향으로 이어질 수 있다는 점에서 반도체 공급·수요 구조에도 변화를 예고한다.",
      "articleCount": 1,
      "relatedArticles": [
        {
          "source": "EE Times",
          "title": "HiPEAC 2026: Reclaiming European Digital Sovereignty",
          "url": "https://www.eetimes.com/hipeac-2026-reclaiming-european-digital-sovereignty/"
        }
      ]
    },
    {
      "id": 4,
      "status": "NEW",
      "title": "삼성전자 2025년 4분기·연간 실적: 메모리·시스템반도체 수요 회복 가속",
      "summary": "삼성전자가 2025년 4분기 및 연간 실적을 공개하며 메모리와 시스템반도체를 포함한 전체 반도체 수요가 구조적 회복 국면에 들어섰음을 시사했다. AI 서버, 모바일, 디스플레이 등 주요 세트 수요와 설비·투자 계획이 함께 제시되며, 업황 바닥 통과 이후 투자 사이클 재진입 여부에 시장의 관심이 집중되고 있다.",
      "articleCount": 1,
      "relatedArticles": [
        {
          "source": "Samsung Newsroom",
          "title": "Samsung Electronics Announces Fourth Quarter and FY 2025 Results",
          "url": "https://news.samsung.com/global/samsung-electronics-announces-fourth-quarter-and-fy-2025-results"
        }
      ]
    },
    {
      "id": 5,
      "status": "NEW",
      "title": "GaN·SiC 전력반도체 확산과 고성능 커패시터 수요 증가",
      "summary": "GaN·SiC 기반 전력 시스템이 서버 전원, 전기차, 산업 인버터 등으로 확산되면서 고주파·고온 환경에 적합한 고성능 커패시터 수요가 빠르게 커지고 있다. 유전체 특성, ESR, 온도 안정성, 수명·패키징 등 세부 스펙이 설계 경쟁력의 핵심 요소로 부상하며, 전력반도체 생태계 전반에 걸친 소재·부품 고도화가 병행되고 있다.",
      "articleCount": 1,
      "relatedArticles": [
        {
          "source": "EE Times",
          "title": "How to Select High-Performance Capacitors for GaN and SiC Power Systems",
          "url": "https://www.eetimes.com/how-to-select-high-performance-capacitors-for-gan-and-sic-power-systems/"
        }
      ]
    }
  ]
}